fortune/__init__.py
fortune/__main__.py
fortune/fortune.py
fortune/strfile.py
fortune/datfiles/LICENSE
fortune/datfiles/art
fortune/datfiles/ascii-art
fortune/datfiles/computers
fortune/datfiles/cookie
fortune/datfiles/debian
fortune/datfiles/definitions
fortune/datfiles/disclaimer
fortune/datfiles/drugs
fortune/datfiles/education
fortune/datfiles/ethnic
fortune/datfiles/food
fortune/datfiles/fortunes
fortune/datfiles/goedel
fortune/datfiles/humorists
fortune/datfiles/kids
fortune/datfiles/knghtbrd
fortune/datfiles/law
fortune/datfiles/linux
fortune/datfiles/linuxcookie
fortune/datfiles/literature
fortune/datfiles/love
fortune/datfiles/magic
fortune/datfiles/medicine
fortune/datfiles/men-women
fortune/datfiles/miscellaneous
fortune/datfiles/news
fortune/datfiles/paradoxum
fortune/datfiles/people
fortune/datfiles/perl
fortune/datfiles/pets
fortune/datfiles/platitudes
fortune/datfiles/politics
fortune/datfiles/pratchett
fortune/datfiles/riddles
fortune/datfiles/science
fortune/datfiles/songs-poems
fortune/datfiles/sports
fortune/datfiles/startrek
fortune/datfiles/tao
fortune/datfiles/translate-me
fortune/datfiles/wisdom
fortune/datfiles/work
fortune/datfiles/zippy
fortune_python-1.1.2.dist-info/licenses/LICENSE
fortune_python-1.1.2.dist-info/METADATA
fortune_python-1.1.2.dist-info/WHEEL
fortune_python-1.1.2.dist-info/entry_points.txt
fortune_python-1.1.2.dist-info/top_level.txt
fortune_python-1.1.2.dist-info/RECORD
