Metadata-Version: 2.4
Name: fortune-python
Version: 1.1.2
Summary: A Fortune clone in Python
Author: James Finnie-Ansley
License-Expression: Apache-2.0
Project-URL: repository, https://codeberg.org/jamesansley/fortune
Keywords: fortune
Requires-Python: >=3.8
License-File: LICENSE
Dynamic: license-file
